MANIFEST.in
setup.cfg
setup.py
django_jsoneditor_ng.egg-info/PKG-INFO
django_jsoneditor_ng.egg-info/SOURCES.txt
django_jsoneditor_ng.egg-info/dependency_links.txt
django_jsoneditor_ng.egg-info/not-zip-safe
django_jsoneditor_ng.egg-info/top_level.txt
jsoneditor/__init__.py
jsoneditor/forms.py
jsoneditor/fields/__init__.py
jsoneditor/fields/django_json_field.py
jsoneditor/fields/django_jsonfield.py
jsoneditor/static/django-jsoneditor/django-jsoneditor.js
jsoneditor/static/jsoneditor/jsoneditor.css
jsoneditor/static/jsoneditor/jsoneditor.js
jsoneditor/static/jsoneditor/img/jsoneditor-icons.png