Metadata-Version: 1.0
Name: django-jsoneditor-ng
Version: 0.0.3
Summary: Django JSON Editor
Home-page: https://github.com/nnseva/django-jsoneditor
Author: Vsevolod Novikov
Author-email: nnseva@gmail.com
License: UNKNOWN
Platform: UNKNOWN
